latex_todo_gen/__init__.py
latex_todo_gen/latex.py
latex_todo_gen/writer.py
latex_todo_gen-0.5.1.dist-info/LICENSE
latex_todo_gen-0.5.1.dist-info/METADATA
latex_todo_gen-0.5.1.dist-info/WHEEL
latex_todo_gen-0.5.1.dist-info/entry_points.txt
latex_todo_gen-0.5.1.dist-info/top_level.txt
latex_todo_gen-0.5.1.dist-info/RECORD
